pysitemap/__init__.py
pysitemap/db.py
pysitemap/models.py
pysitemap/rest.py
pysitemap/validators.py
pysitemap/web_crawler.py
pysitemap/backends/__init__.py
pysitemap/backends/sqlite_todo.py
pysitemap/format_processors/__init__.py
pysitemap/format_processors/text.py
pysitemap/format_processors/xml.py
pysitemap/parsers/__init__.py
pysitemap/parsers/base.py
pysitemap/parsers/lxml_parser.py
pysitemap/parsers/re_parser.py
nix_sitemap_generator-0.10.1.dist-info/LICENSE
nix_sitemap_generator-0.10.1.dist-info/METADATA
nix_sitemap_generator-0.10.1.dist-info/NOTICE
nix_sitemap_generator-0.10.1.dist-info/WHEEL
nix_sitemap_generator-0.10.1.dist-info/top_level.txt
nix_sitemap_generator-0.10.1.dist-info/RECORD
