Metadata-Version: 2.1
Name: nix-sitemap-generator
Version: 0.10.1
Summary: Web crawler and sitemap generator.
Home-page: https://github.com/nixnks/sitemap-generator
Author: Kamo Petrosyan, Nix ツ
Author-email: kamo@haikson.com, nikusunix@gmail.com
License: GPL3
Classifier: Environment :: Web Environment
Classifier: Intended Audience :: Developers
Classifier: License :: OSI Approved :: BSD License
Classifier: Operating System :: OS Independent
Classifier: Programming Language :: Python
Classifier: Programming Language :: Python :: 3
Classifier: Programming Language :: Python :: 3.11
Classifier: Topic :: Software Development :: Libraries :: Python Modules
Requires: asyncio
Requires: lxml
Requires: sqlalchemy
Requires: cssselect
Requires: aiofile
Requires: aiohttp
License-File: LICENSE
License-File: NOTICE
Requires-Dist: asyncio
Requires-Dist: lxml
Requires-Dist: sqlalchemy
Requires-Dist: cssselect
Requires-Dist: aiofile
Requires-Dist: aiohttp
